Metadata-Version: 2.1
Name: facelook
Version: 0.0.1
Summary: face image analysis toolbox
Home-page: https://github.com/wkabbani/facelook
Author: Wassim Kabbani
Author-email: se.wassim.kabbani@gmail.com
License: UNKNOWN
Platform: UNKNOWN
Classifier: Programming Language :: Python :: 3
Classifier: License :: OSI Approved :: MIT License
Classifier: Operating System :: OS Independent
Requires-Python: >=3.5.5
Provides-Extra: dev
